ttsmms/__init__.py
ttsmms/attentions.py
ttsmms/commons.py
ttsmms/data_utils.py
ttsmms/losses.py
ttsmms/mel_processing.py
ttsmms/models.py
ttsmms/modules.py
ttsmms/preprocess.py
ttsmms/transforms.py
ttsmms/utils.py
ttsmms/text/__init__.py
ttsmms/text/cleaners.py
ttsmms/text/symbols.py
ttsmms-0.7.dist-info/LICENSE
ttsmms-0.7.dist-info/METADATA
ttsmms-0.7.dist-info/WHEEL
ttsmms-0.7.dist-info/top_level.txt
ttsmms-0.7.dist-info/RECORD
