Metadata-Version: 2.1
Name: ttsmms
Version: 0.7
Summary: Text-to-speech with The Massively Multilingual Speech (MMS) project
Home-page: https://github.com/wannaphong/ttsmms
Author: Wannaphong
Author-email: wannaphong@yahoo.com
License: MIT License
Project-URL: Source, https://github.com/wannaphong/ttsmms
Keywords: tts,NLP
Classifier: Development Status :: 3 - Alpha
Classifier: Programming Language :: Python :: 3
Classifier: Intended Audience :: Developers
Classifier: License :: OSI Approved :: MIT License
Classifier: Topic :: Scientific/Engineering :: Artificial Intelligence
Classifier: Topic :: Text Processing
Classifier: Topic :: Text Processing :: General
Classifier: Topic :: Text Processing :: Linguistic
Requires-Python: >=3.6
License-File: LICENSE
Requires-Dist: Cython
Requires-Dist: librosa
Requires-Dist: scipy
Requires-Dist: numpy
Requires-Dist: phonemizer
Requires-Dist: torch
Requires-Dist: torchvision
Requires-Dist: Unidecode
Requires-Dist: monotonic-align
